secure_logs/__init__.py
secure_logs/config.py
secure_logs/main.py
secure_logs/middleware.py
secure_logs/utils.py
tests/__init__.py
tests/test_config.py
SecureLogs-0.0.2.dist-info/LICENSE
SecureLogs-0.0.2.dist-info/METADATA
SecureLogs-0.0.2.dist-info/WHEEL
SecureLogs-0.0.2.dist-info/top_level.txt
SecureLogs-0.0.2.dist-info/RECORD
