Metadata-Version: 2.1
Name: SecureLogs
Version: 0.0.2
Summary: A logging library with trace ID support and FastAPI middleware.
Home-page: https://github.com/Happy-Kumar-Sharma/trace-logger
Author: Happy Sharma
Author-email: happycse54@gmail.com
Keywords: secure logging,SecureLogs,python logging module,best logging library,mask sensitive values
Classifier: Programming Language :: Python :: 3
Classifier: License :: OSI Approved :: MIT License
Classifier: Operating System :: OS Independent
Requires-Python: >=3.7
License-File: LICENSE
Requires-Dist: fastapi
Requires-Dist: starlette
